emlid/__init__.py
emlid/devicefactory.py
emlid/deviceinfo.py
emlid/emlidtool.py
emlid/ardupilot/__init__.py
emlid/ardupilot/ardupilot.py
emlid/devices/__init__.py
emlid/devices/device.py
emlid/devices/edgedevice.py
emlid/devices/navio2device.py
emlid/devices/naviodevice.py
emlid/devices/nodevice.py
emlid/devices/tester.py
emlid/devices/configurations/__init__.py
emlid/devices/sensortests/__init__.py
emlid/devices/sensortests/sensortests.py
emlid/rcio/__init__.py
emlid/rcio/blackmagic.py
emlid/rcio/gdb.py
emlid/rcio/updater.py
emlid/rcio/versionchecker.py
emlid/rcio/firmware/__init__.py
emlid/rcio/firmware/firmware.py
emlid/ui/__init__.py
emlid/ui/mainwindow.py
emlid/util/__init__.py
emlid/util/util.py
emlidtool-1.0.8.dist-info/DESCRIPTION.rst
emlidtool-1.0.8.dist-info/METADATA
emlidtool-1.0.8.dist-info/RECORD
emlidtool-1.0.8.dist-info/WHEEL
emlidtool-1.0.8.dist-info/entry_points.txt
emlidtool-1.0.8.dist-info/metadata.json
emlidtool-1.0.8.dist-info/top_level.txt
tests/__init__.py
tests/deviceinfostub.py
tests/devicestub.py
tests/test_arduconfigurator.py
tests/test_device.py
tests/test_emlidtool.py
tests/test_info.py
tests/test_rcio.py
tests/stubtests/__init__.py
tests/stubtests/stubtests.py
