Metadata-Version: 2.0
Name: emlidtool
Version: 1.0.8
Summary: UNKNOWN
Home-page: https://github.com/emlid/emlidtool
Author: Georgii Staroselskii
Author-email: georgii.staroselskii@emlid.com
License: GPL
Platform: UNKNOWN
Requires-Dist: appdirs (==1.4.3)
Requires-Dist: cffi (==1.10.0)
Requires-Dist: coloredlogs (==6.0)
Requires-Dist: coloredlogs (==6.0)
Requires-Dist: coverage (==4.4)
Requires-Dist: humanfriendly (==2.4)
Requires-Dist: navio2 (==1.0.0)
Requires-Dist: packaging (==16.8)
Requires-Dist: pbr (==3.1.1)
Requires-Dist: progressbar2 (==3.34.3)
Requires-Dist: py (==1.4.33)
Requires-Dist: pycparser (==2.17)
Requires-Dist: pyparsing (==2.2.0)
Requires-Dist: six (==1.10.0)
Requires-Dist: smbus-cffi (==0.5.1)
Requires-Dist: spidev (==3.2)
Requires-Dist: termcolor (==1.1.0)
Requires-Dist: urwid (==1.3.1)
